MANIFEST.in
README.rst
cf_purge.py
setup.cfg
setup.py
cf_purge.egg-info/PKG-INFO
cf_purge.egg-info/SOURCES.txt
cf_purge.egg-info/dependency_links.txt
cf_purge.egg-info/entry_points.txt
cf_purge.egg-info/top_level.txt