Metadata-Version: 1.1
Name: cf-purge
Version: 0.1.0
Summary: attr: cf_purge.__doc__
Home-page: https://github.com/ZuluPro/cf-purge
Author: Anthony Monthe (ZuluPro)
Author-email: anthony.monthe@gmail.com
License: UNKNOWN
Keywords: cloud,amazon,cloudfront
Platform: UNKNOWN
Classifier: Development Status :: 4 - Beta
Classifier: Environment :: Console
Classifier: Intended Audience :: Developers
Classifier: Intended Audience :: System Administrators
Classifier: License :: OSI Approved :: BSD License
Classifier: Operating System :: OS Independent
Classifier: Programming Language :: Python
Classifier: Programming Language :: Python :: 3
Classifier: Topic :: Internet
Classifier: Topic :: Internet :: WWW/HTTP :: Site Management
